{"_type":"export","__export_format":4,"__export_date":"2020-07-02T21:20:55.792Z","__export_source":"insomnia.desktop.app:v2020.2.2","resources":[{"_id":"req_487d1ac68a124497ac219ff3264e9bae","authentication":{},"body":{},"created":1593719703875,"description":"","headers":[],"isPrivate":false,"metaSortKey":-1593478646018,"method":"GET","modified":1593724648220,"name":"obtener equipos","parameters":[],"parentId":"fld_50cbb6ff353e41e6bdfbdcdeade03a36","settingDisableRenderRequestBody":false,"settingEncodeUrl":true,"settingFollowRedirects":"global","settingRebuildPath":true,"settingSendCookies":true,"settingStoreCookies":true,"url":"localhost:4000/teams","_type":"request"},{"_id":"fld_50cbb6ff353e41e6bdfbdcdeade03a36","created":1593719703799,"description":"","environment":{},"environmentPropertyOrder":null,"metaSortKey":-1593164344451.5,"modified":1593719703799,"name":"Node, Clase 10 | HA","parentId":"wrk_4ed7e088d3884de3be6d95aa76e89e6a","_type":"request_group"},{"_id":"wrk_4ed7e088d3884de3be6d95aa76e89e6a","created":1591728238447,"description":"","modified":1591728238446,"name":"Imported Workspace","parentId":null,"scope":null,"_type":"workspace"},{"_id":"req_a0d4536f25e0463fa7a5c542301e603f","authentication":{},"body":{},"created":1593719703860,"description":"","headers":[],"isPrivate":false,"metaSortKey":-1593478646012.5,"method":"GET","modified":1593724677474,"name":"obtener equipo","parameters":[],"parentId":"fld_50cbb6ff353e41e6bdfbdcdeade03a36","settingDisableRenderRequestBody":false,"settingEncodeUrl":true,"settingFollowRedirects":"global","settingRebuildPath":true,"settingSendCookies":true,"settingStoreCookies":true,"url":"localhost:4000/teams/5efe3eb877abd56f64ab6e90","_type":"request"},{"_id":"req_6d0eadb68cda4e70919c142751dcee11","authentication":{},"body":{"mimeType":"","text":"{\n\t\"code\": \"na\",\n\t\"name\": \"No Country\",\n\t\"flag\": \"🏳\"\n}"},"created":1593719703867,"description":"","headers":[{"id":"pair_3985abad033344319892f48f0e5edd65","name":"Content-Type","value":"application/json"}],"isPrivate":false,"metaSortKey":-1593478646007,"method":"POST","modified":1593724662337,"name":"añadir equipo","parameters":[],"parentId":"fld_50cbb6ff353e41e6bdfbdcdeade03a36","settingDisableRenderRequestBody":false,"settingEncodeUrl":true,"settingFollowRedirects":"global","settingRebuildPath":true,"settingSendCookies":true,"settingStoreCookies":true,"url":"localhost:4000/teams","_type":"request"},{"_id":"req_e886a019a8f547c898a923bf42492eeb","authentication":{},"body":{},"created":1593719703853,"description":"","headers":[],"isPrivate":false,"metaSortKey":-1593478645922,"method":"DELETE","modified":1593724667426,"name":"eliminar equipo","parameters":[],"parentId":"fld_50cbb6ff353e41e6bdfbdcdeade03a36","settingDisableRenderRequestBody":false,"settingEncodeUrl":true,"settingFollowRedirects":"global","settingRebuildPath":true,"settingSendCookies":true,"settingStoreCookies":true,"url":"localhost:4000/teams/5efbb46492e2d36e0486d4b5","_type":"request"},{"_id":"req_02d6e6654a01447083c302f31164dce8","authentication":{},"body":{"mimeType":"","text":"{\n\t\"code\": \"nc\",\n\t\"name\": \"No Country\",\n\t\"flag\": \"🏳\"\n}"},"created":1593719703848,"description":"","headers":[{"id":"pair_6a01ab60a0ee425c9d40a5703d13328f","name":"Content-Type","value":"application/json"}],"isPrivate":false,"metaSortKey":-1593478645819,"method":"PUT","modified":1593724672705,"name":"actualizar equipo","parameters":[],"parentId":"fld_50cbb6ff353e41e6bdfbdcdeade03a36","settingDisableRenderRequestBody":false,"settingEncodeUrl":true,"settingFollowRedirects":"global","settingRebuildPath":true,"settingSendCookies":true,"settingStoreCookies":true,"url":"localhost:4000/teams/5efe2800dbcd5d3180b11a68","_type":"request"},{"_id":"req_c065d73bf4b4473ca734aad3953e1c92","authentication":{},"body":{"mimeType":"","text":"{\n\t\"flag\": \"🇦🇷\"\n}"},"created":1593719703843,"description":"","headers":[{"id":"pair_ec60da72a8eb44b68a1c9e355dd97764","name":"Content-Type","value":"application/json"}],"isPrivate":false,"metaSortKey":-1593478645802,"method":"PATCH","modified":1593724767233,"name":"parchar equipo","parameters":[],"parentId":"fld_50cbb6ff353e41e6bdfbdcdeade03a36","settingDisableRenderRequestBody":false,"settingEncodeUrl":true,"settingFollowRedirects":"global","settingRebuildPath":true,"settingSendCookies":true,"settingStoreCookies":true,"url":"localhost:4000/teams/5efe2800dbcd5d3180b11a69","_type":"request"},{"_id":"req_207e96c5a7694793b0daa8670bc11a85","authentication":{},"body":{"mimeType":"","text":"{\n\t\"author\": \"Romário\",\n\t\"against\": \"Itália\",\n\t\"minute\": 85\n}"},"created":1593719703836,"description":"","headers":[{"id":"pair_9861995c62f84a76a7f85a38ba471dad","name":"Content-Type","value":"application/json"}],"isPrivate":false,"metaSortKey":-1593478645786,"method":"POST","modified":1593724778601,"name":"añadir gol a equipo","parameters":[],"parentId":"fld_50cbb6ff353e41e6bdfbdcdeade03a36","settingDisableRenderRequestBody":false,"settingEncodeUrl":true,"settingFollowRedirects":"global","settingRebuildPath":true,"settingSendCookies":true,"settingStoreCookies":true,"url":"localhost:4000/teams/5efe3eb877abd56f64ab6e90/goal","_type":"request"},{"_id":"req_1541e9e94ab34d64b79a03e0876e423a","authentication":{},"body":{"mimeType":"","text":"{\n\t\"author\": \"Romário\",\n\t\"against\": \"Itália\",\n\t\"minute\": 84\n}"},"created":1593719703830,"description":"","headers":[{"id":"pair_475eeb486ab94d8fbba62542319cd625","name":"Content-Type","value":"application/json"}],"isPrivate":false,"metaSortKey":-1593478645774,"method":"DELETE","modified":1593724788115,"name":"eliminar gol de equipo","parameters":[],"parentId":"fld_50cbb6ff353e41e6bdfbdcdeade03a36","settingDisableRenderRequestBody":false,"settingEncodeUrl":true,"settingFollowRedirects":"global","settingRebuildPath":true,"settingSendCookies":true,"settingStoreCookies":true,"url":"localhost:4000/teams/5efe3eb877abd56f64ab6e90/goal","_type":"request"},{"_id":"req_b019dcf2f3fe48f5a5c3ac6c92778a12","authentication":{},"body":{"mimeType":"application/json","text":"{\n\t\"find\": {\n\t\t\"author\": \"Romário\",\n\t\t\"against\": \"Itália\",\n\t\t\"minute\": 85\n\t},\n\t\"update\": {\n\t\t\"author\": \"asdf\",\n\t\t\"against\": \"asdf\",\n\t\t\"minute\": 84\n\t}\n}"},"created":1593719703823,"description":"","headers":[{"id":"pair_adbf9319160447ae9cfdfce85f6da6a9","name":"Content-Type","value":"application/json"}],"isPrivate":false,"metaSortKey":-1593478645762,"method":"PATCH","modified":1593724796880,"name":"corregir gol de equipo","parameters":[],"parentId":"fld_50cbb6ff353e41e6bdfbdcdeade03a36","settingDisableRenderRequestBody":false,"settingEncodeUrl":true,"settingFollowRedirects":"global","settingRebuildPath":true,"settingSendCookies":true,"settingStoreCookies":true,"url":"localhost:4000/teams/5efe3eb877abd56f64ab6e90/goal","_type":"request"},{"_id":"req_e05151fb4be7412a9a2eb44947bce043","authentication":{},"body":{},"created":1593719703815,"description":"","headers":[],"isPrivate":false,"metaSortKey":-1593478645754,"method":"GET","modified":1593724820025,"name":"obtener último gol de equipo","parameters":[],"parentId":"fld_50cbb6ff353e41e6bdfbdcdeade03a36","settingDisableRenderRequestBody":false,"settingEncodeUrl":true,"settingFollowRedirects":"global","settingRebuildPath":true,"settingSendCookies":true,"settingStoreCookies":true,"url":"localhost:4000/teams/5efe3eb877abd56f64ab6e90/goal/last","_type":"request"},{"_id":"req_d90b23f5e78346e691227d6634ee5a7b","authentication":{},"body":{},"created":1593719703807,"description":"","headers":[],"isPrivate":false,"metaSortKey":-1593478645738,"method":"DELETE","modified":1593724824289,"name":"eliminar último gol de equipo","parameters":[],"parentId":"fld_50cbb6ff353e41e6bdfbdcdeade03a36","settingDisableRenderRequestBody":false,"settingEncodeUrl":true,"settingFollowRedirects":"global","settingRebuildPath":true,"settingSendCookies":true,"settingStoreCookies":true,"url":"localhost:4000/teams/5efe3eb877abd56f64ab6e90/goal/last","_type":"request"},{"_id":"env_1411d2b5da509719ce76bbdf2de25266776960b2","color":null,"created":1591728256471,"data":{"mailchimpToken":"2ea3dee362a6ce45597a4ba6442fde59-us10"},"dataPropertyOrder":{"&":["mailchimpToken"]},"isPrivate":false,"metaSortKey":1591728256471,"modified":1592239134053,"name":"Base Environment","parentId":"wrk_4ed7e088d3884de3be6d95aa76e89e6a","_type":"environment"},{"_id":"jar_1411d2b5da509719ce76bbdf2de25266776960b2","cookies":[{"creation":"2020-06-15T15:17:48.269Z","domain":"api.mailchimp.com","expires":"2020-06-19T01:51:07.000Z","hostOnly":false,"httpOnly":true,"id":"7917391630204971","key":"ak_bmsc","lastAccessed":"2020-06-18T23:51:07.112Z","maxAge":7200,"path":"/","value":"21D734295CE8E8BC5B59A56CA801DC17C8281C5D100D0000EBFDEB5E4902FC68~plMPFbTL67mytXzGfZ0Rio++wMdp7WrzzKKLWjNOyTiQJ8jf2CEOHdqVj6euOrL8aFiFmNoEVUpDJy8xpJtmqdbOb8SOL020ofn+cxiOY76T2D85mzPdNWyKFAz/yycBCIAecbjUU3npGZampYxsYG1DAFCPAK946+dJevk7iBeWagnNQ+eQD3/zf5EKg+u2T5erxMJ+5Cce434FvEbsFzrW4DJ2k9yJLEfZOtAMe3d7U="},{"creation":"2020-06-15T15:18:12.401Z","domain":"api.mailchimp.com","hostOnly":false,"httpOnly":true,"id":"7646023124746826","key":"bm_sv","lastAccessed":"2020-06-18T23:51:14.059Z","maxAge":0,"path":"/","value":"32D0BC2D2BAC977F65BAEFCC386F8A43~0+wfWiOuRPhqVZ99WMDiI7ocEn4mjx3BFneQ6c1iM0KCLEFOK6er2t+9HSDOB0jz7PWMQaYxRFV3Fcd4jJBpVvTovJ4flvAs6MO0v0SHO8Yy8LeqcVUgr+EeXQC7ABz09GQGYYEu0+iejduLDX0cqqbq2ANnCZeC+SDgLJZmmcc="},{"creation":"2020-06-15T20:30:05.358Z","domain":"mailchimp.com","hostOnly":true,"id":"033866577229410666","key":"_AVESTA_ENVIRONMENT","lastAccessed":"2020-06-15T20:30:05.358Z","path":"/","value":"prod"},{"creation":"2020-06-15T20:30:05.358Z","domain":"mailchimp.com","expires":"2021-06-15T20:30:04.000Z","hostOnly":false,"id":"4543994439860388","key":"_mcid","lastAccessed":"2020-06-15T20:30:05.358Z","maxAge":31536000,"path":"/","value":"1.74423181c8e1fbef2001f9d465ee2a39.7d6ae3a6e6aa2e95e7244f553b22a7f2584cf050c60a2cf3e2a046115fcb9857"},{"creation":"2020-07-01T02:31:31.147Z","domain":"elpais.com.uy","expires":"2020-07-31T02:31:30.000Z","extensions":["SameSite=Lax"],"hostOnly":false,"httpOnly":true,"id":"3722981426618768","key":"__cfduid","lastAccessed":"2020-07-01T02:31:31.147Z","path":"/","value":"df19f1011998dcfd5d59307075dd1bb021593570690"}],"created":1591728256487,"modified":1593570691155,"name":"Default Jar","parentId":"wrk_4ed7e088d3884de3be6d95aa76e89e6a","_type":"cookie_jar"},{"_id":"spc_2653cd35cadd404aaeab266cd273e99b","contentType":"yaml","contents":"","created":1591728238452,"fileName":"Imported Workspace","modified":1591728238452,"parentId":"wrk_4ed7e088d3884de3be6d95aa76e89e6a","_type":"api_spec"}]}